<?xml version="1.0" encoding="UTF-8"?>
<Reports lib="QtRPT" programmer="Aleksey Osipov" email="aliks-os@ukr.net">
  <Report pageHeight="1188" marginsBottom="40" borderColor="" pageNo="1" marginsLeft="40" orientation="0" borderStyle="" border="0" marginsTop="40" marginsRight="40" borderWidth="1" pageWidth="840">
    <ReportBand type="ReportTitle" width="760" name="RepTitleBand" height="665">
      <TContainerField autoHeight="0" width="324" aligmentH="hCenter" fontColor="rgba(0,0,0,255)" printing="1" backgroundColor="rgba(255,255,255,255)" top="12" fontFamily="黑体" height="20" borderRight="rgba(255,255,255,255)" borderLeft="rgba(255,255,255,255)" borderStyle="solid" fontUnderline="1" ZValue="11" borderBottom="rgba(255,255,255,255)" borderTop="rgba(255,255,255,255)" aligmentV="vCenter" groupName="" value="浙 江 大 学 报 销 汇 总 单" textWrap="1" fontItalic="0" fontSize="16" borderColor="rgba(0,0,0,255)" type="label" highlighting="" format="" left="206" name="field1" fontBold="1" borderWidth="1px" fontStrikeout="0"/>
      <TContainerField autoHeight="0" width="200" aligmentH="hLeft" fontColor="rgba(0,0,0,255)" printing="1" backgroundColor="rgba(255,255,255,255)" top="50" fontFamily="黑体" height="20" borderRight="rgba(255,255,255,255)" borderLeft="rgba(255,255,255,255)" borderStyle="solid" fontUnderline="0" ZValue="11" borderBottom="rgba(255,255,255,255)" borderTop="rgba(255,255,255,255)" aligmentV="vCenter" groupName="" value="[20    年    月    日]" textWrap="0" fontItalic="0" fontSize="12" borderColor="rgba(0,0,0,255)" type="label" highlighting="" format="" left="272" name="field2" fontBold="1" borderWidth="1px" fontStrikeout="0"/>
      <TContainerField autoHeight="0" width="200" aligmentH="hLeft" fontColor="rgba(0,0,0,255)" printing="1" backgroundColor="rgba(255,255,255,255)" top="71" fontFamily="黑体" height="20" borderRight="rgba(255,255,255,255)" borderLeft="rgba(255,255,255,255)" borderStyle="solid" fontUnderline="0" ZValue="11" borderBottom="rgba(255,255,255,255)" borderTop="rgba(255,255,255,255)" aligmentV="vCenter" groupName="" value="填写要求： " textWrap="0" fontItalic="0" fontSize="10" borderColor="rgba(0,0,0,255)" type="label" highlighting="" format="" left="15" name="field3" fontBold="1" borderWidth="1px" fontStrikeout="0"/>
      <TContainerField autoHeight="0" width="715" aligmentH="hLeft" fontColor="rgba(0,0,0,255)" printing="1" backgroundColor="rgba(255,255,255,255)" top="90" fontFamily="黑体" height="25" borderRight="rgba(255,255,255,255)" borderLeft="rgba(255,255,255,255)" borderStyle="solid" fontUnderline="0" ZValue="11" borderBottom="rgba(255,255,255,255)" borderTop="rgba(255,255,255,255)" aligmentV="vCenter" groupName="" value="1、按规定项目准确填写；2、每张票据背后由经办人、经费主管等两人签名3、附件张数控制在50张以下。 " textWrap="0" fontItalic="0" fontSize="10" borderColor="rgba(0,0,0,255)" type="label" highlighting="" format="" left="15" name="field4" fontBold="1" borderWidth="1px" fontStrikeout="0"/>
      <TContainerField autoHeight="0" width="96" aligmentH="hLeft" fontColor="rgba(0,0,0,255)" printing="1" backgroundColor="rgba(255,255,255,255)" top="120" fontFamily="SimSun" height="25" borderRight="rgba(0,0,0,255)" borderLeft="rgba(0,0,0,255)" borderStyle="solid" fontUnderline="0" ZValue="11" borderBottom="rgba(0,0,0,255)" borderTop="rgba(0,0,0,255)" aligmentV="vCenter" groupName="" value=" 单位（公章）" textWrap="1" fontItalic="0" fontSize="10" borderColor="rgba(0,0,0,255)" type="label" highlighting="" format="" left="12" name="field5" fontBold="0" borderWidth="1px" fontStrikeout="0"/>
      <TContainerField autoHeight="0" width="232" aligmentH="hCenter" fontColor="rgba(0,0,0,255)" printing="1" backgroundColor="rgba(255,255,255,255)" top="120" fontFamily="SimSun" height="25" borderRight="rgba(0,0,0,255)" borderLeft="rgba(0,0,0,255)" borderStyle="solid" fontUnderline="0" ZValue="11" borderBottom="rgba(0,0,0,255)" borderTop="rgba(0,0,0,255)" aligmentV="vCenter" groupName="" value="[FundsItemCode]" textWrap="0" fontItalic="0" fontSize="9" borderColor="rgba(0,0,0,255)" type="label" highlighting="" format="" left="380" name="field6" fontBold="0" borderWidth="1px" fontStrikeout="0"/>
      <TContainerField autoHeight="0" width="124" aligmentH="hLeft" fontColor="rgba(0,0,0,255)" printing="1" backgroundColor="rgba(255,255,255,255)" top="120" fontFamily="SimSun" height="25" borderRight="rgba(0,0,0,255)" borderLeft="rgba(0,0,0,255)" borderStyle="solid" fontUnderline="0" ZValue="11" borderBottom="rgba(0,0,0,255)" borderTop="rgba(0,0,0,255)" aligmentV="vCenter" groupName="" value="  经费项目代码" textWrap="0" fontItalic="0" fontSize="10" borderColor="rgba(0,0,0,255)" type="label" highlighting="" format="" left="257" name="field7" fontBold="0" borderWidth="1px" fontStrikeout="0"/>
      <TContainerField autoHeight="0" width="82" aligmentH="hLeft" fontColor="rgba(0,0,0,255)" printing="1" backgroundColor="rgba(255,255,255,255)" top="120" fontFamily="SimSun" height="25" borderRight="rgba(0,0,0,255)" borderLeft="rgba(0,0,0,255)" borderStyle="solid" fontUnderline="0" ZValue="11" borderBottom="rgba(0,0,0,255)" borderTop="rgba(0,0,0,255)" aligmentV="vCenter" groupName="" value=" 单据张数 " textWrap="0" fontItalic="0" fontSize="10" borderColor="rgba(0,0,0,255)" type="label" highlighting="" format="" left="611" name="field8" fontBold="0" borderWidth="1px" fontStrikeout="0"/>
      <TContainerField autoHeight="0" width="151" aligmentH="hLeft" fontColor="rgba(0,0,0,255)" printing="1" backgroundColor="rgba(255,255,255,255)" top="120" fontFamily="SimSun" height="25" borderRight="rgba(0,0,0,255)" borderLeft="rgba(0,0,0,255)" borderStyle="solid" fontUnderline="0" ZValue="11" borderBottom="rgba(0,0,0,255)" borderTop="rgba(0,0,0,255)" aligmentV="vCenter" groupName="" value="" textWrap="0" fontItalic="0" fontSize="9" borderColor="rgba(0,0,0,255)" type="label" highlighting="" format="" left="107" name="field9" fontBold="0" borderWidth="1px" fontStrikeout="0"/>
      <TContainerField autoHeight="0" width="56" aligmentH="hCenter" fontColor="rgba(0,0,0,255)" printing="1" backgroundColor="rgba(255,255,255,255)" top="120" fontFamily="SimSun" height="25" borderRight="rgba(0,0,0,255)" borderLeft="rgba(0,0,0,255)" borderStyle="solid" fontUnderline="0" ZValue="11" borderBottom="rgba(0,0,0,255)" borderTop="rgba(0,0,0,255)" aligmentV="vCenter" groupName="" value="[BillCount]" textWrap="0" fontItalic="0" fontSize="10" borderColor="rgba(0,0,0,255)" type="label" highlighting="" format="" left="692" name="field10" fontBold="0" borderWidth="1px" fontStrikeout="0"/>
      <TContainerField autoHeight="0" width="124" aligmentH="hLeft" fontColor="rgba(0,0,0,255)" printing="1" backgroundColor="rgba(255,255,255,255)" top="145" fontFamily="SimSun" height="25" borderRight="rgba(0,0,0,255)" borderLeft="rgba(0,0,0,255)" borderStyle="solid" fontUnderline="0" ZValue="11" borderBottom="rgba(0,0,0,255)" borderTop="rgba(0,0,0,255)" aligmentV="vCenter" groupName="" value="  项         目  " textWrap="1" fontItalic="0" fontSize="10" borderColor="rgba(0,0,0,255)" type="label" highlighting="" format="" left="12" name="field11" fontBold="0" borderWidth="1px" fontStrikeout="0"/>
      <TContainerField autoHeight="0" width="123" aligmentH="hLeft" fontColor="rgba(0,0,0,255)" printing="1" backgroundColor="rgba(255,255,255,255)" top="145" fontFamily="SimSun" height="25" borderRight="rgba(0,0,0,255)" borderLeft="rgba(0,0,0,255)" borderStyle="solid" fontUnderline="0" ZValue="11" borderBottom="rgba(0,0,0,255)" borderTop="rgba(0,0,0,255)" aligmentV="vCenter" groupName="" value="    金      额  " textWrap="1" fontItalic="0" fontSize="10" borderColor="rgba(0,0,0,255)" type="label" highlighting="" format="" left="135" name="field12" fontBold="0" borderWidth="1px" fontStrikeout="0"/>
      <TContainerField autoHeight="0" width="123" aligmentH="hLeft" fontColor="rgba(0,0,0,255)" printing="1" backgroundColor="rgba(255,255,255,255)" top="145" fontFamily="SimSun" height="25" borderRight="rgba(0,0,0,255)" borderLeft="rgba(0,0,0,255)" borderStyle="solid" fontUnderline="0" ZValue="11" borderBottom="rgba(0,0,0,255)" borderTop="rgba(0,0,0,255)" aligmentV="vCenter" groupName="" value="    金      额  " textWrap="1" fontItalic="0" fontSize="10" borderColor="rgba(0,0,0,255)" type="label" highlighting="" format="" left="380" name="field13" fontBold="0" borderWidth="1px" fontStrikeout="0"/>
      <TContainerField autoHeight="0" width="124" aligmentH="hLeft" fontColor="rgba(0,0,0,255)" printing="1" backgroundColor="rgba(255,255,255,255)" top="145" fontFamily="SimSun" height="25" borderRight="rgba(0,0,0,255)" borderLeft="rgba(0,0,0,255)" borderStyle="solid" fontUnderline="0" ZValue="11" borderBottom="rgba(0,0,0,255)" borderTop="rgba(0,0,0,255)" aligmentV="vCenter" groupName="" value="  项         目  " textWrap="1" fontItalic="0" fontSize="10" borderColor="rgba(0,0,0,255)" type="label" highlighting="" format="" left="257" name="field14" fontBold="0" borderWidth="1px" fontStrikeout="0"/>
      <TContainerField autoHeight="0" width="124" aligmentH="hLeft" fontColor="rgba(0,0,0,255)" printing="1" backgroundColor="rgba(255,255,255,255)" top="145" fontFamily="SimSun" height="25" borderRight="rgba(0,0,0,255)" borderLeft="rgba(0,0,0,255)" borderStyle="solid" fontUnderline="0" ZValue="11" borderBottom="rgba(0,0,0,255)" borderTop="rgba(0,0,0,255)" aligmentV="vCenter" groupName="" value="  项         目  " textWrap="1" fontItalic="0" fontSize="10" borderColor="rgba(0,0,0,255)" type="label" highlighting="" format="" left="502" name="field15" fontBold="0" borderWidth="1px" fontStrikeout="0"/>
      <TContainerField autoHeight="0" width="123" aligmentH="hLeft" fontColor="rgba(0,0,0,255)" printing="1" backgroundColor="rgba(255,255,255,255)" top="145" fontFamily="SimSun" height="25" borderRight="rgba(0,0,0,255)" borderLeft="rgba(0,0,0,255)" borderStyle="solid" fontUnderline="0" ZValue="11" borderBottom="rgba(0,0,0,255)" borderTop="rgba(0,0,0,255)" aligmentV="vCenter" groupName="" value="    金      额  " textWrap="1" fontItalic="0" fontSize="10" borderColor="rgba(0,0,0,255)" type="label" highlighting="" format="" left="625" name="field16" fontBold="0" borderWidth="1px" fontStrikeout="0"/>
      <TContainerField autoHeight="0" width="123" aligmentH="hCenter" fontColor="rgba(0,0,0,255)" printing="1" backgroundColor="rgba(255,255,255,255)" top="170" fontFamily="SimSun" height="25" borderRight="rgba(0,0,0,255)" borderLeft="rgba(0,0,0,255)" borderStyle="solid" fontUnderline="0" ZValue="11" borderBottom="rgba(0,0,0,255)" borderTop="rgba(0,0,0,255)" aligmentV="vCenter" groupName="" value="[TrainingFees]" textWrap="1" fontItalic="0" fontSize="10" borderColor="rgba(0,0,0,255)" type="label" highlighting="" format="" left="625" name="field17" fontBold="0" borderWidth="1px" fontStrikeout="0"/>
      <TContainerField autoHeight="0" width="124" aligmentH="hLeft" fontColor="rgba(0,0,0,255)" printing="1" backgroundColor="rgba(255,255,255,255)" top="170" fontFamily="SimSun" height="25" borderRight="rgba(0,0,0,255)" borderLeft="rgba(0,0,0,255)" borderStyle="solid" fontUnderline="0" ZValue="11" borderBottom="rgba(0,0,0,255)" borderTop="rgba(0,0,0,255)" aligmentV="vCenter" groupName="" value="  培    训    费" textWrap="1" fontItalic="0" fontSize="10" borderColor="rgba(0,0,0,255)" type="label" highlighting="" format="" left="502" name="field18" fontBold="0" borderWidth="1px" fontStrikeout="0"/>
      <TContainerField autoHeight="0" width="124" aligmentH="hLeft" fontColor="rgba(0,0,0,255)" printing="1" backgroundColor="rgba(255,255,255,255)" top="170" fontFamily="SimSun" height="25" borderRight="rgba(0,0,0,255)" borderLeft="rgba(0,0,0,255)" borderStyle="solid" fontUnderline="0" ZValue="11" borderBottom="rgba(0,0,0,255)" borderTop="rgba(0,0,0,255)" aligmentV="vCenter" groupName="" value="  实    习    费" textWrap="1" fontItalic="0" fontSize="10" borderColor="rgba(0,0,0,255)" type="label" highlighting="" format="" left="257" name="field19" fontBold="0" borderWidth="1px" fontStrikeout="0"/>
      <TContainerField autoHeight="0" width="123" aligmentH="hCenter" fontColor="rgba(0,0,0,255)" printing="1" backgroundColor="rgba(255,255,255,255)" top="170" fontFamily="SimSun" height="25" borderRight="rgba(0,0,0,255)" borderLeft="rgba(0,0,0,255)" borderStyle="solid" fontUnderline="0" ZValue="11" borderBottom="rgba(0,0,0,255)" borderTop="rgba(0,0,0,255)" aligmentV="vCenter" groupName="" value="[LodgingExpenses]" textWrap="1" fontItalic="0" fontSize="10" borderColor="rgba(0,0,0,255)" type="label" highlighting="" format="" left="380" name="field20" fontBold="0" borderWidth="1px" fontStrikeout="0"/>
      <TContainerField autoHeight="0" width="123" aligmentH="hCenter" fontColor="rgba(0,0,0,255)" printing="1" backgroundColor="rgba(255,255,255,255)" top="170" fontFamily="SimSun" height="25" borderRight="rgba(0,0,0,255)" borderLeft="rgba(0,0,0,255)" borderStyle="solid" fontUnderline="0" ZValue="11" borderBottom="rgba(0,0,0,255)" borderTop="rgba(0,0,0,255)" aligmentV="vCenter" groupName="" value="[LocalTransportation]" textWrap="1" fontItalic="0" fontSize="10" borderColor="rgba(0,0,0,255)" type="label" highlighting="" format="" left="135" name="field21" fontBold="0" borderWidth="1px" fontStrikeout="0"/>
      <TContainerField autoHeight="0" width="124" aligmentH="hLeft" fontColor="rgba(0,0,0,255)" printing="1" backgroundColor="rgba(255,255,255,255)" top="170" fontFamily="SimSun" height="25" borderRight="rgba(0,0,0,255)" borderLeft="rgba(0,0,0,255)" borderStyle="solid" fontUnderline="0" ZValue="11" borderBottom="rgba(0,0,0,255)" borderTop="rgba(0,0,0,255)" aligmentV="vCenter" groupName="" value="  市 内 交 通 费 " textWrap="1" fontItalic="0" fontSize="10" borderColor="rgba(0,0,0,255)" type="label" highlighting="" format="" left="12" name="field22" fontBold="0" borderWidth="1px" fontStrikeout="0"/>
      <TContainerField autoHeight="0" width="124" aligmentH="hLeft" fontColor="rgba(0,0,0,255)" printing="1" backgroundColor="rgba(255,255,255,255)" top="195" fontFamily="SimSun" height="25" borderRight="rgba(0,0,0,255)" borderLeft="rgba(0,0,0,255)" borderStyle="solid" fontUnderline="0" ZValue="11" borderBottom="rgba(0,0,0,255)" borderTop="rgba(0,0,0,255)" aligmentV="vCenter" groupName="" value="  办  公  用  品 " textWrap="1" fontItalic="0" fontSize="10" borderColor="rgba(0,0,0,255)" type="label" highlighting="" format="" left="12" name="field23" fontBold="0" borderWidth="1px" fontStrikeout="0"/>
      <TContainerField autoHeight="0" width="123" aligmentH="hCenter" fontColor="rgba(0,0,0,255)" printing="1" backgroundColor="rgba(255,255,255,255)" top="195" fontFamily="SimSun" height="25" borderRight="rgba(0,0,0,255)" borderLeft="rgba(0,0,0,255)" borderStyle="solid" fontUnderline="0" ZValue="11" borderBottom="rgba(0,0,0,255)" borderTop="rgba(0,0,0,255)" aligmentV="vCenter" groupName="" value="[OfficeSupplies]" textWrap="1" fontItalic="0" fontSize="10" borderColor="rgba(0,0,0,255)" type="label" highlighting="" format="" left="135" name="field24" fontBold="0" borderWidth="1px" fontStrikeout="0"/>
      <TContainerField autoHeight="0" width="123" aligmentH="hCenter" fontColor="rgba(0,0,0,255)" printing="1" backgroundColor="rgba(255,255,255,255)" top="195" fontFamily="SimSun" height="25" borderRight="rgba(0,0,0,255)" borderLeft="rgba(0,0,0,255)" borderStyle="solid" fontUnderline="0" ZValue="11" borderBottom="rgba(0,0,0,255)" borderTop="rgba(0,0,0,255)" aligmentV="vCenter" groupName="" value="[StudentActivityFee]" textWrap="1" fontItalic="0" fontSize="10" borderColor="rgba(0,0,0,255)" type="label" highlighting="" format="" left="380" name="field25" fontBold="0" borderWidth="1px" fontStrikeout="0"/>
      <TContainerField autoHeight="0" width="124" aligmentH="hLeft" fontColor="rgba(0,0,0,255)" printing="1" backgroundColor="rgba(255,255,255,255)" top="195" fontFamily="SimSun" height="25" borderRight="rgba(0,0,0,255)" borderLeft="rgba(0,0,0,255)" borderStyle="solid" fontUnderline="0" ZValue="11" borderBottom="rgba(0,0,0,255)" borderTop="rgba(0,0,0,255)" aligmentV="vCenter" groupName="" value="  学 生 活 动 费" textWrap="1" fontItalic="0" fontSize="10" borderColor="rgba(0,0,0,255)" type="label" highlighting="" format="" left="257" name="field26" fontBold="0" borderWidth="1px" fontStrikeout="0"/>
      <TContainerField autoHeight="0" width="124" aligmentH="hLeft" fontColor="rgba(0,0,0,255)" printing="1" backgroundColor="rgba(255,255,255,255)" top="195" fontFamily="SimSun" height="25" borderRight="rgba(0,0,0,255)" borderLeft="rgba(0,0,0,255)" borderStyle="solid" fontUnderline="0" ZValue="11" borderBottom="rgba(0,0,0,255)" borderTop="rgba(0,0,0,255)" aligmentV="vCenter" groupName="" value="  招    待    费" textWrap="1" fontItalic="0" fontSize="10" borderColor="rgba(0,0,0,255)" type="label" highlighting="" format="" left="502" name="field27" fontBold="0" borderWidth="1px" fontStrikeout="0"/>
      <TContainerField autoHeight="0" width="123" aligmentH="hCenter" fontColor="rgba(0,0,0,255)" printing="1" backgroundColor="rgba(255,255,255,255)" top="195" fontFamily="SimSun" height="25" borderRight="rgba(0,0,0,255)" borderLeft="rgba(0,0,0,255)" borderStyle="solid" fontUnderline="0" ZValue="11" borderBottom="rgba(0,0,0,255)" borderTop="rgba(0,0,0,255)" aligmentV="vCenter" groupName="" value="[EntertainmentExpense]" textWrap="1" fontItalic="0" fontSize="10" borderColor="rgba(0,0,0,255)" type="label" highlighting="" format="" left="625" name="field28" fontBold="0" borderWidth="1px" fontStrikeout="0"/>
      <TContainerField autoHeight="0" width="123" aligmentH="hCenter" fontColor="rgba(0,0,0,255)" printing="1" backgroundColor="rgba(255,255,255,255)" top="220" fontFamily="SimSun" height="25" borderRight="rgba(0,0,0,255)" borderLeft="rgba(0,0,0,255)" borderStyle="solid" fontUnderline="0" ZValue="11" borderBottom="rgba(0,0,0,255)" borderTop="rgba(0,0,0,255)" aligmentV="vCenter" groupName="" value="[ConstructionOfFixedAssets]" textWrap="1" fontItalic="0" fontSize="10" borderColor="rgba(0,0,0,255)" type="label" highlighting="" format="" left="625" name="field29" fontBold="0" borderWidth="1px" fontStrikeout="0"/>
      <TContainerField autoHeight="0" width="124" aligmentH="hLeft" fontColor="rgba(0,0,0,255)" printing="1" backgroundColor="rgba(255,255,255,255)" top="220" fontFamily="SimSun" height="25" borderRight="rgba(0,0,0,255)" borderLeft="rgba(0,0,0,255)" borderStyle="solid" fontUnderline="0" ZValue="11" borderBottom="rgba(0,0,0,255)" borderTop="rgba(0,0,0,255)" aligmentV="vCenter" groupName="" value="  固定资产购建费" textWrap="1" fontItalic="0" fontSize="10" borderColor="rgba(0,0,0,255)" type="label" highlighting="" format="" left="502" name="field30" fontBold="0" borderWidth="1px" fontStrikeout="0"/>
      <TContainerField autoHeight="0" width="124" aligmentH="hLeft" fontColor="rgba(0,0,0,255)" printing="1" backgroundColor="rgba(255,255,255,255)" top="220" fontFamily="SimSun" height="25" borderRight="rgba(0,0,0,255)" borderLeft="rgba(0,0,0,255)" borderStyle="solid" fontUnderline="0" ZValue="11" borderBottom="rgba(0,0,0,255)" borderTop="rgba(0,0,0,255)" aligmentV="vCenter" groupName="" value="  通    讯    费" textWrap="1" fontItalic="0" fontSize="10" borderColor="rgba(0,0,0,255)" type="label" highlighting="" format="" left="257" name="field31" fontBold="0" borderWidth="1px" fontStrikeout="0"/>
      <TContainerField autoHeight="0" width="123" aligmentH="hCenter" fontColor="rgba(0,0,0,255)" printing="1" backgroundColor="rgba(255,255,255,255)" top="220" fontFamily="SimSun" height="25" borderRight="rgba(0,0,0,255)" borderLeft="rgba(0,0,0,255)" borderStyle="solid" fontUnderline="0" ZValue="11" borderBottom="rgba(0,0,0,255)" borderTop="rgba(0,0,0,255)" aligmentV="vCenter" groupName="" value="[Correspondence]" textWrap="1" fontItalic="0" fontSize="10" borderColor="rgba(0,0,0,255)" type="label" highlighting="" format="" left="380" name="field32" fontBold="0" borderWidth="1px" fontStrikeout="0"/>
      <TContainerField autoHeight="0" width="123" aligmentH="hCenter" fontColor="rgba(0,0,0,255)" printing="1" backgroundColor="rgba(255,255,255,255)" top="220" fontFamily="SimSun" height="25" borderRight="rgba(0,0,0,255)" borderLeft="rgba(0,0,0,255)" borderStyle="solid" fontUnderline="0" ZValue="11" borderBottom="rgba(0,0,0,255)" borderTop="rgba(0,0,0,255)" aligmentV="vCenter" groupName="" value="[PurchaseOfProfessionalMaterials]" textWrap="1" fontItalic="0" fontSize="10" borderColor="rgba(0,0,0,255)" type="label" highlighting="" format="" left="135" name="field33" fontBold="0" borderWidth="1px" fontStrikeout="0"/>
      <TContainerField autoHeight="0" width="124" aligmentH="hLeft" fontColor="rgba(0,0,0,255)" printing="1" backgroundColor="rgba(255,255,255,255)" top="220" fontFamily="SimSun" height="25" borderRight="rgba(0,0,0,255)" borderLeft="rgba(0,0,0,255)" borderStyle="solid" fontUnderline="0" ZValue="11" borderBottom="rgba(0,0,0,255)" borderTop="rgba(0,0,0,255)" aligmentV="vCenter" groupName="" value="  专用材料购置费" textWrap="1" fontItalic="0" fontSize="10" borderColor="rgba(0,0,0,255)" type="label" highlighting="" format="" left="12" name="field34" fontBold="0" borderWidth="1px" fontStrikeout="0"/>
      <TContainerField autoHeight="0" width="124" aligmentH="hLeft" fontColor="rgba(0,0,0,255)" printing="1" backgroundColor="rgba(255,255,255,255)" top="245" fontFamily="SimSun" height="25" borderRight="rgba(0,0,0,255)" borderLeft="rgba(0,0,0,255)" borderStyle="solid" fontUnderline="0" ZValue="11" borderBottom="rgba(0,0,0,255)" borderTop="rgba(0,0,0,255)" aligmentV="vCenter" groupName="" value="  实验材料购置费" textWrap="1" fontItalic="0" fontSize="10" borderColor="rgba(0,0,0,255)" type="label" highlighting="" format="" left="12" name="field35" fontBold="0" borderWidth="1px" fontStrikeout="0"/>
      <TContainerField autoHeight="0" width="123" aligmentH="hCenter" fontColor="rgba(0,0,0,255)" printing="1" backgroundColor="rgba(255,255,255,255)" top="245" fontFamily="SimSun" height="25" borderRight="rgba(0,0,0,255)" borderLeft="rgba(0,0,0,255)" borderStyle="solid" fontUnderline="0" ZValue="11" borderBottom="rgba(0,0,0,255)" borderTop="rgba(0,0,0,255)" aligmentV="vCenter" groupName="" value="[PurchaseOfExperimentalMaterials]" textWrap="1" fontItalic="0" fontSize="10" borderColor="rgba(0,0,0,255)" type="label" highlighting="" format="" left="135" name="field36" fontBold="0" borderWidth="1px" fontStrikeout="0"/>
      <TContainerField autoHeight="0" width="123" aligmentH="hCenter" fontColor="rgba(0,0,0,255)" printing="1" backgroundColor="rgba(255,255,255,255)" top="245" fontFamily="SimSun" height="25" borderRight="rgba(0,0,0,255)" borderLeft="rgba(0,0,0,255)" borderStyle="solid" fontUnderline="0" ZValue="11" borderBottom="rgba(0,0,0,255)" borderTop="rgba(0,0,0,255)" aligmentV="vCenter" groupName="" value="[PostFee]" textWrap="1" fontItalic="0" fontSize="10" borderColor="rgba(0,0,0,255)" type="label" highlighting="" format="" left="380" name="field37" fontBold="0" borderWidth="1px" fontStrikeout="0"/>
      <TContainerField autoHeight="0" width="124" aligmentH="hLeft" fontColor="rgba(0,0,0,255)" printing="1" backgroundColor="rgba(255,255,255,255)" top="245" fontFamily="SimSun" height="25" borderRight="rgba(0,0,0,255)" borderLeft="rgba(0,0,0,255)" borderStyle="solid" fontUnderline="0" ZValue="11" borderBottom="rgba(0,0,0,255)" borderTop="rgba(0,0,0,255)" aligmentV="vCenter" groupName="" value="  邮    寄    费" textWrap="1" fontItalic="0" fontSize="10" borderColor="rgba(0,0,0,255)" type="label" highlighting="" format="" left="257" name="field38" fontBold="0" borderWidth="1px" fontStrikeout="0"/>
      <TContainerField autoHeight="0" width="124" aligmentH="hLeft" fontColor="rgba(0,0,0,255)" printing="1" backgroundColor="rgba(255,255,255,255)" top="245" fontFamily="SimSun" height="25" borderRight="rgba(0,0,0,255)" borderLeft="rgba(0,0,0,255)" borderStyle="solid" fontUnderline="0" ZValue="11" borderBottom="rgba(0,0,0,255)" borderTop="rgba(0,0,0,255)" aligmentV="vCenter" groupName="" value="  横       幅" textWrap="1" fontItalic="0" fontSize="10" borderColor="rgba(0,0,0,255)" type="label" highlighting="" format="" left="502" name="field39" fontBold="0" borderWidth="1px" fontStrikeout="0"/>
      <TContainerField autoHeight="0" width="123" aligmentH="hCenter" fontColor="rgba(0,0,0,255)" printing="1" backgroundColor="rgba(255,255,255,255)" top="245" fontFamily="SimSun" height="25" borderRight="rgba(0,0,0,255)" borderLeft="rgba(0,0,0,255)" borderStyle="solid" fontUnderline="0" ZValue="11" borderBottom="rgba(0,0,0,255)" borderTop="rgba(0,0,0,255)" aligmentV="vCenter" groupName="" value="[Streamer]" textWrap="1" fontItalic="0" fontSize="10" borderColor="rgba(0,0,0,255)" type="label" highlighting="" format="" left="625" name="field40" fontBold="0" borderWidth="1px" fontStrikeout="0"/>
      <TContainerField autoHeight="0" width="123" aligmentH="hCenter" fontColor="rgba(0,0,0,255)" printing="1" backgroundColor="rgba(255,255,255,255)" top="270" fontFamily="SimSun" height="25" borderRight="rgba(0,0,0,255)" borderLeft="rgba(0,0,0,255)" borderStyle="solid" fontUnderline="0" ZValue="11" borderBottom="rgba(0,0,0,255)" borderTop="rgba(0,0,0,255)" aligmentV="vCenter" groupName="" value="[Other]" textWrap="1" fontItalic="0" fontSize="10" borderColor="rgba(0,0,0,255)" type="label" highlighting="" format="" left="625" name="field41" fontBold="0" borderWidth="1px" fontStrikeout="0"/>
      <TContainerField autoHeight="0" width="124" aligmentH="hLeft" fontColor="rgba(0,0,0,255)" printing="1" backgroundColor="rgba(255,255,255,255)" top="270" fontFamily="SimSun" height="25" borderRight="rgba(0,0,0,255)" borderLeft="rgba(0,0,0,255)" borderStyle="solid" fontUnderline="0" ZValue="11" borderBottom="rgba(0,0,0,255)" borderTop="rgba(0,0,0,255)" aligmentV="vCenter" groupName="" value="  其       他" textWrap="1" fontItalic="0" fontSize="10" borderColor="rgba(0,0,0,255)" type="label" highlighting="" format="" left="502" name="field42" fontBold="0" borderWidth="1px" fontStrikeout="0"/>
      <TContainerField autoHeight="0" width="124" aligmentH="hLeft" fontColor="rgba(0,0,0,255)" printing="1" backgroundColor="rgba(255,255,255,255)" top="270" fontFamily="SimSun" height="25" borderRight="rgba(0,0,0,255)" borderLeft="rgba(0,0,0,255)" borderStyle="solid" fontUnderline="0" ZValue="11" borderBottom="rgba(0,0,0,255)" borderTop="rgba(0,0,0,255)" aligmentV="vCenter" groupName="" value="  自 备 车 费 用" textWrap="1" fontItalic="0" fontSize="10" borderColor="rgba(0,0,0,255)" type="label" highlighting="" format="" left="257" name="field43" fontBold="0" borderWidth="1px" fontStrikeout="0"/>
      <TContainerField autoHeight="0" width="123" aligmentH="hCenter" fontColor="rgba(0,0,0,255)" printing="1" backgroundColor="rgba(255,255,255,255)" top="270" fontFamily="SimSun" height="25" borderRight="rgba(0,0,0,255)" borderLeft="rgba(0,0,0,255)" borderStyle="solid" fontUnderline="0" ZValue="11" borderBottom="rgba(0,0,0,255)" borderTop="rgba(0,0,0,255)" aligmentV="vCenter" groupName="" value="[SelfServiceCost]" textWrap="1" fontItalic="0" fontSize="10" borderColor="rgba(0,0,0,255)" type="label" highlighting="" format="" left="380" name="field44" fontBold="0" borderWidth="1px" fontStrikeout="0"/>
      <TContainerField autoHeight="0" width="123" aligmentH="hCenter" fontColor="rgba(0,0,0,255)" printing="1" backgroundColor="rgba(255,255,255,255)" top="270" fontFamily="SimSun" height="25" borderRight="rgba(0,0,0,255)" borderLeft="rgba(0,0,0,255)" borderStyle="solid" fontUnderline="0" ZValue="11" borderBottom="rgba(0,0,0,255)" borderTop="rgba(0,0,0,255)" aligmentV="vCenter" groupName="" value="[SportingGoodsPurchaseFee]" textWrap="1" fontItalic="0" fontSize="10" borderColor="rgba(0,0,0,255)" type="label" highlighting="" format="" left="135" name="field45" fontBold="0" borderWidth="1px" fontStrikeout="0"/>
      <TContainerField autoHeight="0" width="124" aligmentH="hLeft" fontColor="rgba(0,0,0,255)" printing="1" backgroundColor="rgba(255,255,255,255)" top="270" fontFamily="SimSun" height="25" borderRight="rgba(0,0,0,255)" borderLeft="rgba(0,0,0,255)" borderStyle="solid" fontUnderline="0" ZValue="11" borderBottom="rgba(0,0,0,255)" borderTop="rgba(0,0,0,255)" aligmentV="vCenter" groupName="" value="  体育用品购置费" textWrap="1" fontItalic="0" fontSize="10" borderColor="rgba(0,0,0,255)" type="label" highlighting="" format="" left="12" name="field46" fontBold="0" borderWidth="1px" fontStrikeout="0"/>
      <TContainerField autoHeight="0" width="124" aligmentH="hLeft" fontColor="rgba(0,0,0,255)" printing="1" backgroundColor="rgba(255,255,255,255)" top="295" fontFamily="SimSun" height="25" borderRight="rgba(0,0,0,255)" borderLeft="rgba(0,0,0,255)" borderStyle="solid" fontUnderline="0" ZValue="11" borderBottom="rgba(0,0,0,255)" borderTop="rgba(0,0,0,255)" aligmentV="vCenter" groupName="" value="  资 料 复 印 费" textWrap="1" fontItalic="0" fontSize="10" borderColor="rgba(0,0,0,255)" type="label" highlighting="" format="" left="12" name="field47" fontBold="0" borderWidth="1px" fontStrikeout="0"/>
      <TContainerField autoHeight="0" width="123" aligmentH="hCenter" fontColor="rgba(0,0,0,255)" printing="1" backgroundColor="rgba(255,255,255,255)" top="295" fontFamily="SimSun" height="25" borderRight="rgba(0,0,0,255)" borderLeft="rgba(0,0,0,255)" borderStyle="solid" fontUnderline="0" ZValue="11" borderBottom="rgba(0,0,0,255)" borderTop="rgba(0,0,0,255)" aligmentV="vCenter" groupName="" value="[XeroxFee]" textWrap="1" fontItalic="0" fontSize="10" borderColor="rgba(0,0,0,255)" type="label" highlighting="" format="" left="135" name="field48" fontBold="0" borderWidth="1px" fontStrikeout="0"/>
      <TContainerField autoHeight="0" width="123" aligmentH="hCenter" fontColor="rgba(0,0,0,255)" printing="1" backgroundColor="rgba(255,255,255,255)" top="295" fontFamily="SimSun" height="25" borderRight="rgba(0,0,0,255)" borderLeft="rgba(0,0,0,255)" borderStyle="solid" fontUnderline="0" ZValue="11" borderBottom="rgba(0,0,0,255)" borderTop="rgba(0,0,0,255)" aligmentV="vCenter" groupName="" value="[MotorVehicleMaintenance]" textWrap="1" fontItalic="0" fontSize="10" borderColor="rgba(0,0,0,255)" type="label" highlighting="" format="" left="380" name="field49" fontBold="0" borderWidth="1px" fontStrikeout="0"/>
      <TContainerField autoHeight="0" width="124" aligmentH="hLeft" fontColor="rgba(0,0,0,255)" printing="1" backgroundColor="rgba(255,255,255,255)" top="295" fontFamily="SimSun" height="25" borderRight="rgba(0,0,0,255)" borderLeft="rgba(0,0,0,255)" borderStyle="solid" fontUnderline="0" ZValue="11" borderBottom="rgba(0,0,0,255)" borderTop="rgba(0,0,0,255)" aligmentV="vCenter" groupName="" value="  机动车辆维修费" textWrap="1" fontItalic="0" fontSize="10" borderColor="rgba(0,0,0,255)" type="label" highlighting="" format="" left="257" name="field50" fontBold="0" borderWidth="1px" fontStrikeout="0"/>
      <TContainerField autoHeight="0" width="124" aligmentH="hLeft" fontColor="rgba(0,0,0,255)" printing="1" backgroundColor="rgba(255,255,255,255)" top="295" fontFamily="SimSun" height="25" borderRight="rgba(0,0,0,255)" borderLeft="rgba(0,0,0,255)" borderStyle="solid" fontUnderline="0" ZValue="11" borderBottom="rgba(0,0,0,255)" borderTop="rgba(0,0,0,255)" aligmentV="vCenter" groupName="" value="" textWrap="1" fontItalic="0" fontSize="10" borderColor="rgba(0,0,0,255)" type="label" highlighting="" format="" left="502" name="field51" fontBold="0" borderWidth="1px" fontStrikeout="0"/>
      <TContainerField autoHeight="0" width="123" aligmentH="hLeft" fontColor="rgba(0,0,0,255)" printing="1" backgroundColor="rgba(255,255,255,255)" top="295" fontFamily="SimSun" height="25" borderRight="rgba(0,0,0,255)" borderLeft="rgba(0,0,0,255)" borderStyle="solid" fontUnderline="0" ZValue="11" borderBottom="rgba(0,0,0,255)" borderTop="rgba(0,0,0,255)" aligmentV="vCenter" groupName="" value="" textWrap="1" fontItalic="0" fontSize="10" borderColor="rgba(0,0,0,255)" type="label" highlighting="" format="" left="625" name="field52" fontBold="0" borderWidth="1px" fontStrikeout="0"/>
      <TContainerField autoHeight="0" width="123" aligmentH="hLeft" fontColor="rgba(0,0,0,255)" printing="1" backgroundColor="rgba(255,255,255,255)" top="320" fontFamily="SimSun" height="25" borderRight="rgba(0,0,0,255)" borderLeft="rgba(0,0,0,255)" borderStyle="solid" fontUnderline="0" ZValue="11" borderBottom="rgba(0,0,0,255)" borderTop="rgba(0,0,0,255)" aligmentV="vCenter" groupName="" value="" textWrap="1" fontItalic="0" fontSize="10" borderColor="rgba(0,0,0,255)" type="label" highlighting="" format="" left="625" name="field53" fontBold="0" borderWidth="1px" fontStrikeout="0"/>
      <TContainerField autoHeight="0" width="124" aligmentH="hLeft" fontColor="rgba(0,0,0,255)" printing="1" backgroundColor="rgba(255,255,255,255)" top="320" fontFamily="SimSun" height="25" borderRight="rgba(0,0,0,255)" borderLeft="rgba(0,0,0,255)" borderStyle="solid" fontUnderline="0" ZValue="11" borderBottom="rgba(0,0,0,255)" borderTop="rgba(0,0,0,255)" aligmentV="vCenter" groupName="" value="" textWrap="1" fontItalic="0" fontSize="10" borderColor="rgba(0,0,0,255)" type="label" highlighting="" format="" left="502" name="field54" fontBold="0" borderWidth="1px" fontStrikeout="0"/>
      <TContainerField autoHeight="0" width="124" aligmentH="hLeft" fontColor="rgba(0,0,0,255)" printing="1" backgroundColor="rgba(255,255,255,255)" top="320" fontFamily="SimSun" height="25" borderRight="rgba(0,0,0,255)" borderLeft="rgba(0,0,0,255)" borderStyle="solid" fontUnderline="0" ZValue="11" borderBottom="rgba(0,0,0,255)" borderTop="rgba(0,0,0,255)" aligmentV="vCenter" groupName="" value="  办公设备维修费" textWrap="1" fontItalic="0" fontSize="10" borderColor="rgba(0,0,0,255)" type="label" highlighting="" format="" left="257" name="field55" fontBold="0" borderWidth="1px" fontStrikeout="0"/>
      <TContainerField autoHeight="0" width="123" aligmentH="hCenter" fontColor="rgba(0,0,0,255)" printing="1" backgroundColor="rgba(255,255,255,255)" top="320" fontFamily="SimSun" height="25" borderRight="rgba(0,0,0,255)" borderLeft="rgba(0,0,0,255)" borderStyle="solid" fontUnderline="0" ZValue="11" borderBottom="rgba(0,0,0,255)" borderTop="rgba(0,0,0,255)" aligmentV="vCenter" groupName="" value="[OfficeEquipmentMaintenance]" textWrap="1" fontItalic="0" fontSize="10" borderColor="rgba(0,0,0,255)" type="label" highlighting="" format="" left="380" name="field56" fontBold="0" borderWidth="1px" fontStrikeout="0"/>
      <TContainerField autoHeight="0" width="123" aligmentH="hCenter" fontColor="rgba(0,0,0,255)" printing="1" backgroundColor="rgba(255,255,255,255)" top="320" fontFamily="SimSun" height="25" borderRight="rgba(0,0,0,255)" borderLeft="rgba(0,0,0,255)" borderStyle="solid" fontUnderline="0" ZValue="11" borderBottom="rgba(0,0,0,255)" borderTop="rgba(0,0,0,255)" aligmentV="vCenter" groupName="" value="[Typography]" textWrap="1" fontItalic="0" fontSize="10" borderColor="rgba(0,0,0,255)" type="label" highlighting="" format="" left="135" name="field57" fontBold="0" borderWidth="1px" fontStrikeout="0"/>
      <TContainerField autoHeight="0" width="124" aligmentH="hLeft" fontColor="rgba(0,0,0,255)" printing="1" backgroundColor="rgba(255,255,255,255)" top="320" fontFamily="SimSun" height="25" borderRight="rgba(0,0,0,255)" borderLeft="rgba(0,0,0,255)" borderStyle="solid" fontUnderline="0" ZValue="11" borderBottom="rgba(0,0,0,255)" borderTop="rgba(0,0,0,255)" aligmentV="vCenter" groupName="" value="  版 面 印 刷 费" textWrap="1" fontItalic="0" fontSize="10" borderColor="rgba(0,0,0,255)" type="label" highlighting="" format="" left="12" name="field58" fontBold="0" borderWidth="1px" fontStrikeout="0"/>
      <TContainerField autoHeight="0" width="124" aligmentH="hLeft" fontColor="rgba(0,0,0,255)" printing="1" backgroundColor="rgba(255,255,255,255)" top="345" fontFamily="SimSun" height="25" borderRight="rgba(0,0,0,255)" borderLeft="rgba(0,0,0,255)" borderStyle="solid" fontUnderline="0" ZValue="11" borderBottom="rgba(0,0,0,255)" borderTop="rgba(0,0,0,255)" aligmentV="vCenter" groupName="" value="  材料测试加工费" textWrap="1" fontItalic="0" fontSize="10" borderColor="rgba(0,0,0,255)" type="label" highlighting="" format="" left="12" name="field59" fontBold="0" borderWidth="1px" fontStrikeout="0"/>
      <TContainerField autoHeight="0" width="123" aligmentH="hCenter" fontColor="rgba(0,0,0,255)" printing="1" backgroundColor="rgba(255,255,255,255)" top="345" fontFamily="SimSun" height="25" borderRight="rgba(0,0,0,255)" borderLeft="rgba(0,0,0,255)" borderStyle="solid" fontUnderline="0" ZValue="11" borderBottom="rgba(0,0,0,255)" borderTop="rgba(0,0,0,255)" aligmentV="vCenter" groupName="" value="[MaterialTestingAndProcessingFee]" textWrap="1" fontItalic="0" fontSize="10" borderColor="rgba(0,0,0,255)" type="label" highlighting="" format="" left="135" name="field60" fontBold="0" borderWidth="1px" fontStrikeout="0"/>
      <TContainerField autoHeight="0" width="123" aligmentH="hCenter" fontColor="rgba(0,0,0,255)" printing="1" backgroundColor="rgba(255,255,255,255)" top="345" fontFamily="SimSun" height="25" borderRight="rgba(0,0,0,255)" borderLeft="rgba(0,0,0,255)" borderStyle="solid" fontUnderline="0" ZValue="11" borderBottom="rgba(0,0,0,255)" borderTop="rgba(0,0,0,255)" aligmentV="vCenter" groupName="" value="[EquipmentMaintenanceFee]" textWrap="1" fontItalic="0" fontSize="10" borderColor="rgba(0,0,0,255)" type="label" highlighting="" format="" left="380" name="field61" fontBold="0" borderWidth="1px" fontStrikeout="0"/>
      <TContainerField autoHeight="0" width="124" aligmentH="hLeft" fontColor="rgba(0,0,0,255)" printing="1" backgroundColor="rgba(255,255,255,255)" top="345" fontFamily="SimSun" height="25" borderRight="rgba(0,0,0,255)" borderLeft="rgba(0,0,0,255)" borderStyle="solid" fontUnderline="0" ZValue="11" borderBottom="rgba(0,0,0,255)" borderTop="rgba(0,0,0,255)" aligmentV="vCenter" groupName="" value="  仪器设备维修费" textWrap="1" fontItalic="0" fontSize="10" borderColor="rgba(0,0,0,255)" type="label" highlighting="" format="" left="257" name="field62" fontBold="0" borderWidth="1px" fontStrikeout="0"/>
      <TContainerField autoHeight="0" width="124" aligmentH="hLeft" fontColor="rgba(0,0,0,255)" printing="1" backgroundColor="rgba(255,255,255,255)" top="345" fontFamily="SimSun" height="25" borderRight="rgba(0,0,0,255)" borderLeft="rgba(0,0,0,255)" borderStyle="solid" fontUnderline="0" ZValue="11" borderBottom="rgba(0,0,0,255)" borderTop="rgba(0,0,0,255)" aligmentV="vCenter" groupName="" value="" textWrap="1" fontItalic="0" fontSize="10" borderColor="rgba(0,0,0,255)" type="label" highlighting="" format="" left="502" name="field63" fontBold="0" borderWidth="1px" fontStrikeout="0"/>
      <TContainerField autoHeight="0" width="123" aligmentH="hLeft" fontColor="rgba(0,0,0,255)" printing="1" backgroundColor="rgba(255,255,255,255)" top="345" fontFamily="SimSun" height="25" borderRight="rgba(0,0,0,255)" borderLeft="rgba(0,0,0,255)" borderStyle="solid" fontUnderline="0" ZValue="11" borderBottom="rgba(0,0,0,255)" borderTop="rgba(0,0,0,255)" aligmentV="vCenter" groupName="" value="" textWrap="1" fontItalic="0" fontSize="10" borderColor="rgba(0,0,0,255)" type="label" highlighting="" format="" left="625" name="field64" fontBold="0" borderWidth="1px" fontStrikeout="0"/>
      <TContainerField autoHeight="0" width="182" aligmentH="hLeft" fontColor="rgba(0,0,0,255)" printing="1" backgroundColor="rgba(255,255,255,255)" top="370" fontFamily="SimSun" height="25" borderRight="rgba(0,0,0,255)" borderLeft="rgba(0,0,0,255)" borderStyle="solid" fontUnderline="0" ZValue="11" borderBottom="rgba(0,0,0,255)" borderTop="rgba(0,0,0,255)" aligmentV="vCenter" groupName="" value="     合计人民币（大写）" textWrap="1" fontItalic="0" fontSize="10" borderColor="rgba(0,0,0,255)" type="label" highlighting="" format="" left="12" name="field65" fontBold="0" borderWidth="1px" fontStrikeout="0"/>
      <TContainerField autoHeight="0" width="555" aligmentH="hLeft" fontColor="rgba(0,0,0,255)" printing="1" backgroundColor="rgba(255,255,255,255)" top="370" fontFamily="SimSun" height="25" borderRight="rgba(0,0,0,255)" borderLeft="rgba(0,0,0,255)" borderStyle="solid" fontUnderline="0" ZValue="11" borderBottom="rgba(0,0,0,255)" borderTop="rgba(0,0,0,255)" aligmentV="vCenter" groupName="" value="[CapitalRMB]" textWrap="1" fontItalic="0" fontSize="10" borderColor="rgba(0,0,0,255)" type="label" highlighting="" format="" left="193" name="field66" fontBold="0" borderWidth="1px" fontStrikeout="0"/>
      <TContainerField autoHeight="0" width="123" aligmentH="hLeft" fontColor="rgba(0,0,0,255)" printing="1" backgroundColor="rgba(255,255,255,255)" top="395" fontFamily="SimSun" height="25" borderRight="rgba(0,0,0,255)" borderLeft="rgba(0,0,0,255)" borderStyle="solid" fontUnderline="0" ZValue="11" borderBottom="rgba(0,0,0,255)" borderTop="rgba(0,0,0,255)" aligmentV="vCenter" groupName="" value="     转卡金额" textWrap="1" fontItalic="0" fontSize="10" borderColor="rgba(0,0,0,255)" type="label" highlighting="" format="" left="625" name="field67" fontBold="0" borderWidth="1px" fontStrikeout="0"/>
      <TContainerField autoHeight="0" width="245" aligmentH="hLeft" fontColor="rgba(0,0,0,255)" printing="1" backgroundColor="rgba(255,255,255,255)" top="395" fontFamily="SimSun" height="25" borderRight="rgba(0,0,0,255)" borderLeft="rgba(0,0,0,255)" borderStyle="solid" fontUnderline="0" ZValue="11" borderBottom="rgba(0,0,0,255)" borderTop="rgba(0,0,0,255)" aligmentV="vCenter" groupName="" value="银行（建行□农行□中信□工行□中行□）" textWrap="1" fontItalic="0" fontSize="9" borderColor="rgba(0,0,0,255)" type="label" highlighting="" format="" left="381" name="field68" fontBold="0" borderWidth="1px" fontStrikeout="0"/>
      <TContainerField autoHeight="0" width="78" aligmentH="hLeft" fontColor="rgba(0,0,0,255)" printing="1" backgroundColor="rgba(255,255,255,255)" top="395" fontFamily="SimSun" height="25" borderRight="rgba(0,0,0,255)" borderLeft="rgba(0,0,0,255)" borderStyle="solid" fontUnderline="0" ZValue="11" borderBottom="rgba(0,0,0,255)" borderTop="rgba(0,0,0,255)" aligmentV="vCenter" groupName="" value="  姓   名" textWrap="1" fontItalic="0" fontSize="10" borderColor="rgba(0,0,0,255)" type="label" highlighting="" format="" left="304" name="field69" fontBold="0" borderWidth="1px" fontStrikeout="0"/>
      <TContainerField autoHeight="0" width="112" aligmentH="hLeft" fontColor="rgba(0,0,0,255)" printing="1" backgroundColor="rgba(255,255,255,255)" top="395" fontFamily="SimSun" height="25" borderRight="rgba(0,0,0,255)" borderLeft="rgba(0,0,0,255)" borderStyle="solid" fontUnderline="0" ZValue="11" borderBottom="rgba(0,0,0,255)" borderTop="rgba(0,0,0,255)" aligmentV="vCenter" groupName="" value="   工（学）号" textWrap="1" fontItalic="0" fontSize="10" borderColor="rgba(0,0,0,255)" type="label" highlighting="" format="" left="193" name="field70" fontBold="0" borderWidth="1px" fontStrikeout="0"/>
      <TContainerField autoHeight="0" width="112" aligmentH="hCenter" fontColor="rgba(0,0,0,255)" printing="1" backgroundColor="rgba(255,255,255,255)" top="420" fontFamily="SimSun" height="25" borderRight="rgba(0,0,0,255)" borderLeft="rgba(0,0,0,255)" borderStyle="solid" fontUnderline="0" ZValue="11" borderBottom="rgba(0,0,0,255)" borderTop="rgba(0,0,0,255)" aligmentV="vCenter" groupName="" value="[SchoolWorkNumber_1]" textWrap="1" fontItalic="0" fontSize="10" borderColor="rgba(0,0,0,255)" type="label" highlighting="" format="" left="193" name="field71" fontBold="0" borderWidth="1px" fontStrikeout="0"/>
      <TContainerField autoHeight="0" width="78" aligmentH="hCenter" fontColor="rgba(0,0,0,255)" printing="1" backgroundColor="rgba(255,255,255,255)" top="420" fontFamily="SimSun" height="25" borderRight="rgba(0,0,0,255)" borderLeft="rgba(0,0,0,255)" borderStyle="solid" fontUnderline="0" ZValue="11" borderBottom="rgba(0,0,0,255)" borderTop="rgba(0,0,0,255)" aligmentV="vCenter" groupName="" value="[Name_1]" textWrap="1" fontItalic="0" fontSize="10" borderColor="rgba(0,0,0,255)" type="label" highlighting="" format="" left="304" name="field72" fontBold="0" borderWidth="1px" fontStrikeout="0"/>
      <TContainerField autoHeight="0" width="245" aligmentH="hCenter" fontColor="rgba(0,0,0,255)" printing="1" backgroundColor="rgba(255,255,255,255)" top="420" fontFamily="SimSun" height="25" borderRight="rgba(0,0,0,255)" borderLeft="rgba(0,0,0,255)" borderStyle="solid" fontUnderline="0" ZValue="11" borderBottom="rgba(0,0,0,255)" borderTop="rgba(0,0,0,255)" aligmentV="vCenter" groupName="" value="[Bank_1]" textWrap="1" fontItalic="0" fontSize="9" borderColor="rgba(0,0,0,255)" type="label" highlighting="" format="" left="381" name="field73" fontBold="0" borderWidth="1px" fontStrikeout="0"/>
      <TContainerField autoHeight="0" width="123" aligmentH="hCenter" fontColor="rgba(0,0,0,255)" printing="1" backgroundColor="rgba(255,255,255,255)" top="420" fontFamily="SimSun" height="25" borderRight="rgba(0,0,0,255)" borderLeft="rgba(0,0,0,255)" borderStyle="solid" fontUnderline="0" ZValue="11" borderBottom="rgba(0,0,0,255)" borderTop="rgba(0,0,0,255)" aligmentV="vCenter" groupName="" value="[Money_1]" textWrap="1" fontItalic="0" fontSize="10" borderColor="rgba(0,0,0,255)" type="label" highlighting="" format="" left="625" name="field74" fontBold="0" borderWidth="1px" fontStrikeout="0"/>
      <TContainerField autoHeight="0" width="182" aligmentH="hLeft" fontColor="rgba(0,0,0,255)" printing="1" backgroundColor="rgba(255,255,255,255)" top="395" fontFamily="SimSun" height="100" borderRight="rgba(0,0,0,255)" borderLeft="rgba(0,0,0,255)" borderStyle="solid" fontUnderline="0" ZValue="11" borderBottom="rgba(0,0,0,255)" borderTop="rgba(0,0,0,255)" aligmentV="vCenter" groupName="" value="转卡信息（报销转入银行卡&#xa;需填写，转入多人可加行）" textWrap="0" fontItalic="0" fontSize="10" borderColor="rgba(0,0,0,255)" type="label" highlighting="" format="" left="12" name="field75" fontBold="0" borderWidth="1px" fontStrikeout="0"/>
      <TContainerField autoHeight="0" width="82" aligmentH="hLeft" fontColor="rgba(0,0,0,255)" printing="1" backgroundColor="rgba(255,255,255,255)" top="517" fontFamily="黑体" height="20" borderRight="rgba(255,255,255,255)" borderLeft="rgba(255,255,255,255)" borderStyle="solid" fontUnderline="0" ZValue="11" borderBottom="rgba(255,255,255,255)" borderTop="rgba(255,255,255,255)" aligmentV="vCenter" groupName="" value="经费主管：" textWrap="0" fontItalic="0" fontSize="12" borderColor="rgba(0,0,0,255)" type="label" highlighting="" format="" left="16" name="field76" fontBold="1" borderWidth="1px" fontStrikeout="0"/>
      <TContainerField autoHeight="0" width="64" aligmentH="hLeft" fontColor="rgba(0,0,0,255)" printing="1" backgroundColor="rgba(255,255,255,255)" top="513" fontFamily="黑体" height="20" borderRight="rgba(255,255,255,255)" borderLeft="rgba(255,255,255,255)" borderStyle="solid" fontUnderline="0" ZValue="11" borderBottom="rgba(255,255,255,255)" borderTop="rgba(255,255,255,255)" aligmentV="vCenter" groupName="" value="经办人：" textWrap="0" fontItalic="0" fontSize="12" borderColor="rgba(0,0,0,255)" type="label" highlighting="" format="" left="269" name="field77" fontBold="1" borderWidth="1px" fontStrikeout="0"/>
      <TContainerField autoHeight="0" width="82" aligmentH="hLeft" fontColor="rgba(0,0,0,255)" printing="1" backgroundColor="rgba(255,255,255,255)" top="511" fontFamily="黑体" height="20" borderRight="rgba(255,255,255,255)" borderLeft="rgba(255,255,255,255)" borderStyle="solid" fontUnderline="0" ZValue="11" borderBottom="rgba(255,255,255,255)" borderTop="rgba(255,255,255,255)" aligmentV="vCenter" groupName="" value="联系电话：" textWrap="0" fontItalic="0" fontSize="12" borderColor="rgba(0,0,0,255)" type="label" highlighting="" format="" left="495" name="field78" fontBold="1" borderWidth="1px" fontStrikeout="0"/>
      <TContainerField autoHeight="0" width="150" aligmentH="hCenter" fontColor="rgba(0,0,0,255)" printing="1" backgroundColor="rgba(255,255,255,255)" top="515" fontFamily="SimSun" height="20" borderRight="rgba(255,255,255,255)" borderLeft="rgba(255,255,255,255)" borderStyle="solid" fontUnderline="0" ZValue="11" borderBottom="rgba(0,0,0,255)" borderTop="rgba(255,255,255,255)" aligmentV="vCenter" groupName="" value="[FinanceSupervisor]" textWrap="0" fontItalic="0" fontSize="9" borderColor="rgba(0,0,0,255)" type="label" highlighting="" format="" left="106" name="field79" fontBold="0" borderWidth="1px" fontStrikeout="0"/>
      <TContainerField autoHeight="0" width="150" aligmentH="hCenter" fontColor="rgba(0,0,0,255)" printing="1" backgroundColor="rgba(255,255,255,255)" top="513" fontFamily="SimSun" height="20" borderRight="rgba(255,255,255,255)" borderLeft="rgba(255,255,255,255)" borderStyle="solid" fontUnderline="0" ZValue="11" borderBottom="rgba(0,0,0,255)" borderTop="rgba(255,255,255,255)" aligmentV="vCenter" groupName="" value="[operator]" textWrap="0" fontItalic="0" fontSize="9" borderColor="rgba(0,0,0,255)" type="label" highlighting="" format="" left="337" name="field80" fontBold="0" borderWidth="1px" fontStrikeout="0"/>
      <TContainerField autoHeight="0" width="150" aligmentH="hCenter" fontColor="rgba(0,0,0,255)" printing="1" backgroundColor="rgba(255,255,255,255)" top="513" fontFamily="SimSun" height="20" borderRight="rgba(255,255,255,255)" borderLeft="rgba(255,255,255,255)" borderStyle="solid" fontUnderline="0" ZValue="11" borderBottom="rgba(0,0,0,255)" borderTop="rgba(255,255,255,255)" aligmentV="vCenter" groupName="" value="[PhoneNumber]" textWrap="0" fontItalic="0" fontSize="9" borderColor="rgba(0,0,0,255)" type="label" highlighting="" format="" left="588" name="field81" fontBold="0" borderWidth="1px" fontStrikeout="0"/>
      <TContainerField autoHeight="0" width="123" aligmentH="hCenter" fontColor="rgba(0,0,0,255)" printing="1" backgroundColor="rgba(255,255,255,255)" top="445" fontFamily="SimSun" height="25" borderRight="rgba(0,0,0,255)" borderLeft="rgba(0,0,0,255)" borderStyle="solid" fontUnderline="0" ZValue="11" borderBottom="rgba(0,0,0,255)" borderTop="rgba(0,0,0,255)" aligmentV="vCenter" groupName="" value="[Money_2]" textWrap="1" fontItalic="0" fontSize="10" borderColor="rgba(0,0,0,255)" type="label" highlighting="" format="" left="625" name="field82" fontBold="0" borderWidth="1px" fontStrikeout="0"/>
      <TContainerField autoHeight="0" width="245" aligmentH="hCenter" fontColor="rgba(0,0,0,255)" printing="1" backgroundColor="rgba(255,255,255,255)" top="445" fontFamily="SimSun" height="25" borderRight="rgba(0,0,0,255)" borderLeft="rgba(0,0,0,255)" borderStyle="solid" fontUnderline="0" ZValue="11" borderBottom="rgba(0,0,0,255)" borderTop="rgba(0,0,0,255)" aligmentV="vCenter" groupName="" value="[Bank_2]" textWrap="1" fontItalic="0" fontSize="9" borderColor="rgba(0,0,0,255)" type="label" highlighting="" format="" left="381" name="field83" fontBold="0" borderWidth="1px" fontStrikeout="0"/>
      <TContainerField autoHeight="0" width="78" aligmentH="hCenter" fontColor="rgba(0,0,0,255)" printing="1" backgroundColor="rgba(255,255,255,255)" top="445" fontFamily="SimSun" height="25" borderRight="rgba(0,0,0,255)" borderLeft="rgba(0,0,0,255)" borderStyle="solid" fontUnderline="0" ZValue="11" borderBottom="rgba(0,0,0,255)" borderTop="rgba(0,0,0,255)" aligmentV="vCenter" groupName="" value="[Name_2]" textWrap="1" fontItalic="0" fontSize="10" borderColor="rgba(0,0,0,255)" type="label" highlighting="" format="" left="304" name="field84" fontBold="0" borderWidth="1px" fontStrikeout="0"/>
      <TContainerField autoHeight="0" width="112" aligmentH="hCenter" fontColor="rgba(0,0,0,255)" printing="1" backgroundColor="rgba(255,255,255,255)" top="445" fontFamily="SimSun" height="25" borderRight="rgba(0,0,0,255)" borderLeft="rgba(0,0,0,255)" borderStyle="solid" fontUnderline="0" ZValue="11" borderBottom="rgba(0,0,0,255)" borderTop="rgba(0,0,0,255)" aligmentV="vCenter" groupName="" value="[SchoolWorkNumber_2]" textWrap="1" fontItalic="0" fontSize="10" borderColor="rgba(0,0,0,255)" type="label" highlighting="" format="" left="193" name="field85" fontBold="0" borderWidth="1px" fontStrikeout="0"/>
      <TContainerField autoHeight="0" width="112" aligmentH="hCenter" fontColor="rgba(0,0,0,255)" printing="1" backgroundColor="rgba(255,255,255,255)" top="470" fontFamily="SimSun" height="25" borderRight="rgba(0,0,0,255)" borderLeft="rgba(0,0,0,255)" borderStyle="solid" fontUnderline="0" ZValue="11" borderBottom="rgba(0,0,0,255)" borderTop="rgba(0,0,0,255)" aligmentV="vCenter" groupName="" value="[SchoolWorkNumber_3]" textWrap="1" fontItalic="0" fontSize="10" borderColor="rgba(0,0,0,255)" type="label" highlighting="" format="" left="193" name="field86" fontBold="0" borderWidth="1px" fontStrikeout="0"/>
      <TContainerField autoHeight="0" width="78" aligmentH="hCenter" fontColor="rgba(0,0,0,255)" printing="1" backgroundColor="rgba(255,255,255,255)" top="470" fontFamily="SimSun" height="25" borderRight="rgba(0,0,0,255)" borderLeft="rgba(0,0,0,255)" borderStyle="solid" fontUnderline="0" ZValue="11" borderBottom="rgba(0,0,0,255)" borderTop="rgba(0,0,0,255)" aligmentV="vCenter" groupName="" value="[Name_3]" textWrap="1" fontItalic="0" fontSize="10" borderColor="rgba(0,0,0,255)" type="label" highlighting="" format="" left="304" name="field87" fontBold="0" borderWidth="1px" fontStrikeout="0"/>
      <TContainerField autoHeight="0" width="245" aligmentH="hCenter" fontColor="rgba(0,0,0,255)" printing="1" backgroundColor="rgba(255,255,255,255)" top="470" fontFamily="SimSun" height="25" borderRight="rgba(0,0,0,255)" borderLeft="rgba(0,0,0,255)" borderStyle="solid" fontUnderline="0" ZValue="11" borderBottom="rgba(0,0,0,255)" borderTop="rgba(0,0,0,255)" aligmentV="vCenter" groupName="" value="[Bank_3]" textWrap="1" fontItalic="0" fontSize="9" borderColor="rgba(0,0,0,255)" type="label" highlighting="" format="" left="381" name="field88" fontBold="0" borderWidth="1px" fontStrikeout="0"/>
      <TContainerField autoHeight="0" width="123" aligmentH="hCenter" fontColor="rgba(0,0,0,255)" printing="1" backgroundColor="rgba(255,255,255,255)" top="470" fontFamily="SimSun" height="25" borderRight="rgba(0,0,0,255)" borderLeft="rgba(0,0,0,255)" borderStyle="solid" fontUnderline="0" ZValue="11" borderBottom="rgba(0,0,0,255)" borderTop="rgba(0,0,0,255)" aligmentV="vCenter" groupName="" value="[Money_3]" textWrap="1" fontItalic="0" fontSize="10" borderColor="rgba(0,0,0,255)" type="label" highlighting="" format="" left="625" name="field89" fontBold="0" borderWidth="1px" fontStrikeout="0"/>
    </ReportBand>
  </Report>
</Reports>
